era_5g_interface/__init__.py
era_5g_interface/channels.py
era_5g_interface/client_channels.py
era_5g_interface/exceptions.py
era_5g_interface/frame_decoder.py
era_5g_interface/frame_encoder.py
era_5g_interface/interface_helpers.py
era_5g_interface/measuring.py
era_5g_interface/py.typed
era_5g_interface/server_channels.py
era_5g_interface/task_handler_internal_q.py
era_5g_interface/dataclasses/__init__.py
era_5g_interface/dataclasses/control_command.py
era_5g_interface/utils/__init__.py
era_5g_interface/utils/locked_set.py
era_5g_interface/utils/rate_timer.py
era_5g_interface-0.10.1.dist-info/METADATA
era_5g_interface-0.10.1.dist-info/WHEEL
era_5g_interface-0.10.1.dist-info/namespace_packages.txt
era_5g_interface-0.10.1.dist-info/top_level.txt
era_5g_interface-0.10.1.dist-info/RECORD
