Metadata-Version: 2.1
Name: era-5g-interface
Version: 0.10.1
Summary: An interface for 5G-ERA Network Applications
Author: Michal Kapinus
Author-email: ikapinus@fit.vutbr.cz
License: LGPL
Classifier: Programming Language :: Python :: 3
Classifier: License :: OSI Approved :: GNU Lesser General Public License v3 (LGPLv3)
Classifier: Operating System :: OS Independent
Classifier: Intended Audience :: Developers
Requires-Python: >=3.8
Requires-Dist: av (>=11.0.0)
Requires-Dist: lz4 (>=4.3.2)
Requires-Dist: numpy (>=1.24.4)
Requires-Dist: opencv-python (>=4.7)
Requires-Dist: psutil (>=5.9.8)
Requires-Dist: python-socketio[client] (>=5.10.0)
Requires-Dist: types-psutil (>=5.9.5)
Requires-Dist: types-requests (>=2.31.0.10)
Requires-Dist: types-ujson (>=5.8.0.1)
Requires-Dist: ujson (>=5.8.0)
